LICENSE.txt
MANIFEST.in
README.md
setup.cfg
setup.py
pypachy/__init__.py
pypachy/pfs_client.py
pypachy/pfs_pb2.py
pypachy/pfs_pb2_grpc.py
pypachy/pps_client.py
pypachy/pps_pb2.py
pypachy/pps_pb2_grpc.py
pypachy.egg-info/PKG-INFO
pypachy.egg-info/SOURCES.txt
pypachy.egg-info/dependency_links.txt
pypachy.egg-info/requires.txt
pypachy.egg-info/top_level.txt