Metadata-Version: 1.1
Name: pypachy
Version: 0.1.5
Summary: Python Pachyderm Client
Home-page: https://github.com/kalugny/pypachy
Author: Yuval Kalugny
Author-email: kalugny@gmail.com
License: MIT
Keywords: pachyderm
Platform: UNKNOWN
Classifier: Development Status :: 3 - Alpha
Classifier: Intended Audience :: Developers
Classifier: License :: OSI Approved :: MIT License
Classifier: Programming Language :: Python :: 2.7
Classifier: Programming Language :: Python :: 3
Classifier: Programming Language :: Python :: 3.3
Classifier: Programming Language :: Python :: 3.4
Classifier: Programming Language :: Python :: 3.5
Classifier: Programming Language :: Python :: 3.6
